{
  "info": {
    "_postman_id": "dbbc27f1-1188-4025-8d22-4f925a2cde4e",
    "name": "Shopper stack",
    "schema": "https://schema.getpostman.com/json/collection/v2.1.0/collection.json",
    "_exporter_id": "53775599",
    "_collection_link": "https://go.postman.co/collection/53775599-dbbc27f1-1188-4025-8d22-4f925a2cde4e?source=collection_link"
  },
  "item": [
    {
      "name": "Shopper Profile",
      "item": [
        {
          "name": "Register Shopper",
          "event": [
            {
              "listen": "test",
              "script": {
                "exec": [
                  "pm.test(\"Status code is 201\", function () {\r",
                  "    pm.response.to.have.status(201);\r",
                  "});\r",
                  "\r",
                  "let res = pm.response.json();\r",
                  "\r",
                  "let shopperId = res.data.userId;\r",
                  "pm.environment.set(\"shopperId\", shopperId);\r",
                  "\r",
                  "let email = res.data.email;\r",
                  "pm.environment.set(\"shopperEmail\", email);\r",
                  "\r",
                  "pm.environment.set(\"shopperPwd\", \"I52_yamI\");\r",
                  ""
                ],
                "type": "text/javascript",
                "packages": {},
                "requests": {}
              }
            },
            {
              "listen": "prerequest",
              "script": {
                "exec": [
                  ""
                ],
                "type": "text/javascript",
                "packages": {},
                "requests": {}
              }
            }
          ],
          "request": {
            "auth": {
              "type": "noauth"
            },
            "method": "POST",
            "header": [],
            "body": {
              "mode": "raw",
              "raw": "{\r\n    \"city\": \"Jaipur\",\r\n    \"country\": \"India\",\r\n    \"email\": \"threeswordstyle@gmail.com\",\r\n    \"firstName\": \"Rishabh\",\r\n    \"gender\": \"MALE\",\r\n    \"lastName\": \"Pant\",\r\n    \"password\": \"I52_yamI\",\r\n    \"phone\": 9950026400,\r\n    \"state\": \"Karnataka\",\r\n    \"zoneId\": \"ALPHA\"\r\n}",
              "options": {
                "raw": {
                  "language": "json"
                }
              }
            },
            "url": {
              "raw": "{{base_url}}/shoppers?zoneId=ALPHA",
              "host": [
                "{{base_url}}"
              ],
              "path": [
                "shoppers"
              ],
              "query": [
                {
                  "key": "zoneId",
                  "value": "ALPHA"
                }
              ]
            }
          },
          "response": []
        },
        {
          "name": "Login Shopper",
          "event": [
            {
              "listen": "test",
              "script": {
                "exec": [
                  "pm.test(\"Status code is 200\", function () {\r",
                  "    pm.response.to.have.status(200);\r",
                  "});\r",
                  "let res = pm.response.json();\r",
                  "let token = res.data.jwtToken\r",
                  "pm.environment.set(\"token\", token);\r",
                  "\r",
                  "pm.test(\"validate schema\",function(){\r",
                  "    const schema = {\r",
                  "        type: \"object\",\r",
                  "        properties:{\r",
                  "                \"statusCode\": {type: \"number\"},\r",
                  "                \"message\": {type:\"string\"},\r",
                  "                \"data\": {\r",
                  "                    \"userId\": {type: \"number\"},\r",
                  "                    \"email\": {type:\"string\"},\r",
                  "                    \"role\": {type:\"string\"},\r",
                  "                    \"status\": {type:\"string\"},\r",
                  "                    \"createdDateTime\": null,\r",
                  "                    \"firstName\": {type:\"string\"},\r",
                  "                    \"lastName\": {type:\"string\"},\r",
                  "                    \"city\": {type:\"string\"},\r",
                  "                    \"state\": {type:\"string\"},\r",
                  "                    \"country\": {type:\"string\"},\r",
                  "                    \"zoneId\": {type:\"string\"},\r",
                  "                    \"imageId\": null,\r",
                  "                    \"jwtToken\": {type:\"string\"}\r",
                  "                }\r",
                  "            \r",
                  "        }\r",
                  "    }\r",
                  "    pm.response.to.have.jsonSchema(schema);\r",
                  "});"
                ],
                "type": "text/javascript",
                "packages": {},
                "requests": {}
              }
            },
            {
              "listen": "prerequest",
              "script": {
                "exec": [
                  ""
                ],
                "type": "text/javascript",
                "packages": {},
                "requests": {}
              }
            }
          ],
          "request": {
            "auth": {
              "type": "noauth"
            },
            "method": "POST",
            "header": [],
            "body": {
              "mode": "raw",
              "raw": "{\r\n  \"email\": \"{{shopperEmail}}\",\r\n  \"password\": \"{{shopperPwd}}\",\r\n  \"role\": \"SHOPPER\"\r\n}",
              "options": {
                "raw": {
                  "language": "json"
                }
              }
            },
            "url": {
              "raw": "{{base_url}}/users/login",
              "host": [
                "{{base_url}}"
              ],
              "path": [
                "users",
                "login"
              ]
            }
          },
          "response": []
        },
        {
          "name": "Find Shopper",
          "request": {
            "auth": {
              "type": "bearer",
              "bearer": [
                {
                  "key": "token",
                  "value": "eyJhbGciOiJIUzI1NiJ9.eyJzdWIiOiJ0aHJlZXN3b3Jkc3R5bGVAZ21haWwuY29tIFNIT1BQRVIiLCJleHAiOjE3NzU4MzQyNDQsImlhdCI6MTc3NTc5ODI0NH0.aTHeyGY3QY_qF8UqVTcxAu_m6gwQq47ylvTnQW2ch78",
                  "type": "string"
                }
              ]
            },
            "method": "GET",
            "header": [],
            "url": {
              "raw": "{{base_url}}/shoppers/{{shopperId}}",
              "host": [
                "{{base_url}}"
              ],
              "path": [
                "shoppers",
                "{{shopperId}}"
              ]
            }
          },
          "response": []
        },
        {
          "name": "Update Shopper Detailes",
          "request": {
            "auth": {
              "type": "bearer",
              "bearer": [
                {
                  "key": "token",
                  "value": "eyJhbGciOiJIUzI1NiJ9.eyJzdWIiOiJ0aHJlZXN3b3Jkc3R5bGVAZ21haWwuY29tIFNIT1BQRVIiLCJleHAiOjE3NzU4MzQyNDQsImlhdCI6MTc3NTc5ODI0NH0.aTHeyGY3QY_qF8UqVTcxAu_m6gwQq47ylvTnQW2ch78",
                  "type": "string"
                }
              ]
            },
            "method": "PATCH",
            "header": [],
            "body": {
              "mode": "raw",
              "raw": "{\r\n  \"city\": \"Onigashima\",\r\n  \"country\": \"Wano\",\r\n  \"email\": \"threeswordstyle@gmail.com\",\r\n  \"firstName\": \"Roronova\",\r\n  \"gender\": \"MALE\",\r\n  \"lastName\": \"Zoro\",\r\n  \"password\": \"I52_yamI\",\r\n  \"phone\": 9950026400,\r\n  \"state\": \"FlowerCapital\",\r\n  \"zoneId\": \"string\"\r\n}",
              "options": {
                "raw": {
                  "language": "json"
                }
              }
            },
            "url": {
              "raw": "{{base_url}}/shoppers/{{shopperId}}",
              "host": [
                "{{base_url}}"
              ],
              "path": [
                "shoppers",
                "{{shopperId}}"
              ]
            }
          },
          "response": []
        }
      ]
    },
    {
      "name": "Product Action",
      "item": [
        {
          "name": "Return Default",
          "request": {
            "auth": {
              "type": "bearer",
              "bearer": [
                {
                  "key": "token",
                  "value": "eyJhbGciOiJIUzI1NiJ9.eyJzdWIiOiJ0aHJlZXN3b3Jkc3R5bGVAZ21haWwuY29tIFNIT1BQRVIiLCJleHAiOjE3NzU4MzQyNDQsImlhdCI6MTc3NTc5ODI0NH0.aTHeyGY3QY_qF8UqVTcxAu_m6gwQq47ylvTnQW2ch78",
                  "type": "string"
                }
              ]
            },
            "method": "GET",
            "header": [],
            "url": {
              "raw": "{{base_url}}/products/alpha?zoneId=ALPHA",
              "host": [
                "{{base_url}}"
              ],
              "path": [
                "products",
                "alpha"
              ],
              "query": [
                {
                  "key": "zoneId",
                  "value": "ALPHA"
                }
              ]
            }
          },
          "response": []
        }
      ]
    },
    {
      "name": "Shopper Address",
      "item": [
        {
          "name": "Get All Address",
          "event": [
            {
              "listen": "test",
              "script": {
                "exec": [
                  ""
                ],
                "type": "text/javascript",
                "packages": {},
                "requests": {}
              }
            },
            {
              "listen": "prerequest",
              "script": {
                "exec": [
                  ""
                ],
                "type": "text/javascript",
                "packages": {},
                "requests": {}
              }
            }
          ],
          "request": {
            "auth": {
              "type": "bearer",
              "bearer": [
                {
                  "key": "token",
                  "value": "eyJhbGciOiJIUzI1NiJ9.eyJzdWIiOiJ0aHJlZXN3b3Jkc3R5bGVAZ21haWwuY29tIFNIT1BQRVIiLCJleHAiOjE3NzU4MzM2MTUsImlhdCI6MTc3NTc5NzYxNX0.zEW1CKNWQj1gBh98R7O4s_Ay0Gm7PiTautfEPv86ivk",
                  "type": "string"
                }
              ]
            },
            "method": "GET",
            "header": [],
            "url": {
              "raw": "{{base_url}}/shoppers/{{shopperId}}/address",
              "host": [
                "{{base_url}}"
              ],
              "path": [
                "shoppers",
                "{{shopperId}}",
                "address"
              ]
            }
          },
          "response": []
        },
        {
          "name": "Add NewAddress",
          "event": [
            {
              "listen": "test",
              "script": {
                "exec": [
                  "pm.test(\"Status code is 201\", function () {\r",
                  "    pm.response.to.have.status(201);\r",
                  "});\r",
                  "let res  = pm.response.json();\r",
                  "pm.environment.set(\"addressId\" , res.data.addressId);"
                ],
                "type": "text/javascript",
                "packages": {},
                "requests": {}
              }
            },
            {
              "listen": "prerequest",
              "script": {
                "exec": [
                  ""
                ],
                "type": "text/javascript",
                "packages": {},
                "requests": {}
              }
            }
          ],
          "request": {
            "auth": {
              "type": "bearer",
              "bearer": [
                {
                  "key": "token",
                  "value": "eyJhbGciOiJIUzI1NiJ9.eyJzdWIiOiJ0aHJlZXN3b3Jkc3R5bGVAZ21haWwuY29tIFNIT1BQRVIiLCJleHAiOjE3NzU4MzM2MTUsImlhdCI6MTc3NTc5NzYxNX0.zEW1CKNWQj1gBh98R7O4s_Ay0Gm7PiTautfEPv86ivk",
                  "type": "string"
                }
              ]
            },
            "method": "POST",
            "header": [],
            "body": {
              "mode": "raw",
              "raw": "{\r\n  \"addressId\": 5,\r\n  \"buildingInfo\": \"JECRC UNIVERSITY\",\r\n  \"city\": \"banglore\",\r\n  \"country\": \"India\",\r\n  \"landmark\": \"xyz\",\r\n  \"name\": \"Engineering\",\r\n  \"phone\": \"9876546789\",\r\n  \"pincode\": \"560010\",\r\n  \"state\": \"Rajasthan\",\r\n  \"streetInfo\": \"Goner Road\",\r\n  \"type\": \"string\"\r\n}",
              "options": {
                "raw": {
                  "language": "json"
                }
              }
            },
            "url": {
              "raw": "{{base_url}}/shoppers/{{shopperId}}/address",
              "host": [
                "{{base_url}}"
              ],
              "path": [
                "shoppers",
                "{{shopperId}}",
                "address"
              ]
            }
          },
          "response": []
        },
        {
          "name": "Get Particular Address",
          "request": {
            "auth": {
              "type": "bearer",
              "bearer": [
                {
                  "key": "token",
                  "value": "eyJhbGciOiJIUzI1NiJ9.eyJzdWIiOiJ0aHJlZXN3b3Jkc3R5bGVAZ21haWwuY29tIFNIT1BQRVIiLCJleHAiOjE3NzU4MzQyNDQsImlhdCI6MTc3NTc5ODI0NH0.aTHeyGY3QY_qF8UqVTcxAu_m6gwQq47ylvTnQW2ch78",
                  "type": "string"
                }
              ]
            },
            "method": "GET",
            "header": [],
            "url": {
              "raw": "{{base_url}}/shoppers/{{shopperId}}/address/{{addressId}}",
              "host": [
                "{{base_url}}"
              ],
              "path": [
                "shoppers",
                "{{shopperId}}",
                "address",
                "{{addressId}}"
              ]
            }
          },
          "response": []
        },
        {
          "name": "Update Address",
          "event": [
            {
              "listen": "test",
              "script": {
                "exec": [
                  "pm.test(\"Status code is 200\", function () {\r",
                  "    pm.response.to.have.status(200);\r",
                  "});\r",
                  "\r",
                  "let res = pm.response.json();\r",
                  "\r",
                  "pm.environment.set(\"addressID\" , res.data.addressId);"
                ],
                "type": "text/javascript",
                "packages": {},
                "requests": {}
              }
            },
            {
              "listen": "prerequest",
              "script": {
                "exec": [
                  ""
                ],
                "type": "text/javascript",
                "packages": {},
                "requests": {}
              }
            }
          ],
          "request": {
            "auth": {
              "type": "bearer",
              "bearer": [
                {
                  "key": "token",
                  "value": "eyJhbGciOiJIUzI1NiJ9.eyJzdWIiOiJ0aHJlZXN3b3Jkc3R5bGVAZ21haWwuY29tIFNIT1BQRVIiLCJleHAiOjE3NzU4MzQyNDQsImlhdCI6MTc3NTc5ODI0NH0.aTHeyGY3QY_qF8UqVTcxAu_m6gwQq47ylvTnQW2ch78",
                  "type": "string"
                }
              ]
            },
            "method": "PUT",
            "header": [],
            "body": {
              "mode": "raw",
              "raw": "{\r\n  \"addressId\": 5,\r\n  \"buildingInfo\": \"JECRC UNIVERSITY\",\r\n  \"city\": \"Banglore\",\r\n  \"country\": \"India\",\r\n  \"landmark\": \"HightStreet\",\r\n  \"name\": \"Engineering\",\r\n  \"phone\": \"9876546789\",\r\n  \"pincode\": \"560010\",\r\n  \"state\": \"Rajasthan\",\r\n  \"streetInfo\": \"MI Road\",\r\n  \"type\": \"string\"\r\n}",
              "options": {
                "raw": {
                  "language": "json"
                }
              }
            },
            "url": {
              "raw": "{{base_url}}/shoppers/{{shopperId}}/address/{{addressId}}",
              "host": [
                "{{base_url}}"
              ],
              "path": [
                "shoppers",
                "{{shopperId}}",
                "address",
                "{{addressId}}"
              ]
            }
          },
          "response": []
        },
        {
          "name": "New Request",
          "request": {
            "auth": {
              "type": "bearer",
              "bearer": [
                {
                  "key": "token",
                  "value": "eyJhbGciOiJIUzI1NiJ9.eyJzdWIiOiJ0aHJlZXN3b3Jkc3R5bGVAZ21haWwuY29tIFNIT1BQRVIiLCJleHAiOjE3NzU4MzQyNDQsImlhdCI6MTc3NTc5ODI0NH0.aTHeyGY3QY_qF8UqVTcxAu_m6gwQq47ylvTnQW2ch78",
                  "type": "string"
                }
              ]
            },
            "method": "DELETE",
            "header": [],
            "url": {
              "raw": "{{base_url}}/shoppers/{{shopperId}}/address/{{addressId}}",
              "host": [
                "{{base_url}}"
              ],
              "path": [
                "shoppers",
                "{{shopperId}}",
                "address",
                "{{addressId}}"
              ]
            }
          },
          "response": []
        }
      ]
    },
    {
      "name": "Shopper Wishlist",
      "item": [
        {
          "name": "Get all Product from Wishlist",
          "request": {
            "auth": {
              "type": "bearer",
              "bearer": [
                {
                  "key": "token",
                  "value": "eyJhbGciOiJIUzI1NiJ9.eyJzdWIiOiJ0aHJlZXN3b3Jkc3R5bGVAZ21haWwuY29tIFNIT1BQRVIiLCJleHAiOjE3NzU4MzQyNDQsImlhdCI6MTc3NTc5ODI0NH0.aTHeyGY3QY_qF8UqVTcxAu_m6gwQq47ylvTnQW2ch78",
                  "type": "string"
                }
              ]
            },
            "method": "GET",
            "header": [],
            "url": {
              "raw": "{{base_url}}/shoppers/{{shopperId}}/wishlist",
              "host": [
                "{{base_url}}"
              ],
              "path": [
                "shoppers",
                "{{shopperId}}",
                "wishlist"
              ]
            }
          },
          "response": []
        },
        {
          "name": "Add to Wishlist",
          "event": [
            {
              "listen": "test",
              "script": {
                "exec": [
                  ""
                ],
                "type": "text/javascript",
                "packages": {},
                "requests": {}
              }
            },
            {
              "listen": "prerequest",
              "script": {
                "exec": [],
                "type": "text/javascript"
              }
            }
          ],
          "request": {
            "auth": {
              "type": "bearer",
              "bearer": [
                {
                  "key": "token",
                  "value": "eyJhbGciOiJIUzI1NiJ9.eyJzdWIiOiJ0aHJlZXN3b3Jkc3R5bGVAZ21haWwuY29tIFNIT1BQRVIiLCJleHAiOjE3NzU4MzQyNDQsImlhdCI6MTc3NTc5ODI0NH0.aTHeyGY3QY_qF8UqVTcxAu_m6gwQq47ylvTnQW2ch78",
                  "type": "string"
                }
              ]
            },
            "method": "POST",
            "header": [],
            "body": {
              "mode": "raw",
              "raw": "{\r\n  \"productId\": 57,\r\n  \"quantity\": 1\r\n}",
              "options": {
                "raw": {
                  "language": "json"
                }
              }
            },
            "url": {
              "raw": "{{base_url}}/shoppers/{{shopperId}}/wishlist",
              "host": [
                "{{base_url}}"
              ],
              "path": [
                "shoppers",
                "{{shopperId}}",
                "wishlist"
              ]
            }
          },
          "response": []
        },
        {
          "name": "Remove from Wishlist",
          "request": {
            "auth": {
              "type": "bearer",
              "bearer": [
                {
                  "key": "token",
                  "value": "eyJhbGciOiJIUzI1NiJ9.eyJzdWIiOiJ0aHJlZXN3b3Jkc3R5bGVAZ21haWwuY29tIFNIT1BQRVIiLCJleHAiOjE3NzU4MzQyNDQsImlhdCI6MTc3NTc5ODI0NH0.aTHeyGY3QY_qF8UqVTcxAu_m6gwQq47ylvTnQW2ch78",
                  "type": "string"
                }
              ]
            },
            "method": "DELETE",
            "header": [],
            "url": {
              "raw": "{{base_url}}/shoppers/{{shopperId}}/wishlist/{{productId}}",
              "host": [
                "{{base_url}}"
              ],
              "path": [
                "shoppers",
                "{{shopperId}}",
                "wishlist",
                "{{productId}}"
              ]
            }
          },
          "response": []
        }
      ]
    },
    {
      "name": "Shopper Cart",
      "item": [
        {
          "name": "Get all Products from Cart",
          "request": {
            "auth": {
              "type": "bearer",
              "bearer": [
                {
                  "key": "token",
                  "value": "eyJhbGciOiJIUzI1NiJ9.eyJzdWIiOiJ0aHJlZXN3b3Jkc3R5bGVAZ21haWwuY29tIFNIT1BQRVIiLCJleHAiOjE3NzU4MzQyNDQsImlhdCI6MTc3NTc5ODI0NH0.aTHeyGY3QY_qF8UqVTcxAu_m6gwQq47ylvTnQW2ch78",
                  "type": "string"
                }
              ]
            },
            "method": "GET",
            "header": [],
            "url": {
              "raw": "{{base_url}}/shoppers/{{shopperId}}/carts",
              "host": [
                "{{base_url}}"
              ],
              "path": [
                "shoppers",
                "{{shopperId}}",
                "carts"
              ]
            }
          },
          "response": []
        },
        {
          "name": "Add Product to Cart",
          "event": [
            {
              "listen": "test",
              "script": {
                "exec": [
                  "pm.test(\"Status code is 200\", function () {\r",
                  "    pm.response.to.have.status(200);\r",
                  "});\r",
                  "let res  = pm.response.json();\r",
                  "pm.environment.set(\"itemId\" , res.data.itemId);"
                ],
                "type": "text/javascript",
                "packages": {},
                "requests": {}
              }
            },
            {
              "listen": "prerequest",
              "script": {
                "exec": [
                  ""
                ],
                "type": "text/javascript",
                "packages": {},
                "requests": {}
              }
            }
          ],
          "request": {
            "auth": {
              "type": "bearer",
              "bearer": [
                {
                  "key": "token",
                  "value": "eyJhbGciOiJIUzI1NiJ9.eyJzdWIiOiJ0aHJlZXN3b3Jkc3R5bGVAZ21haWwuY29tIFNIT1BQRVIiLCJleHAiOjE3NzU4MzQyNDQsImlhdCI6MTc3NTc5ODI0NH0.aTHeyGY3QY_qF8UqVTcxAu_m6gwQq47ylvTnQW2ch78",
                  "type": "string"
                }
              ]
            },
            "method": "POST",
            "header": [],
            "body": {
              "mode": "raw",
              "raw": "{\r\n  \"productId\": 57,\r\n  \"quantity\": 1\r\n}",
              "options": {
                "raw": {
                  "language": "json"
                }
              }
            },
            "url": {
              "raw": "{{base_url}}/shoppers/{{shopperId}}/carts",
              "host": [
                "{{base_url}}"
              ],
              "path": [
                "shoppers",
                "{{shopperId}}",
                "carts"
              ]
            }
          },
          "response": []
        },
        {
          "name": "Update a Product in Cart",
          "event": [
            {
              "listen": "test",
              "script": {
                "exec": [
                  "pm.test(\"Status code is 200\", function () {\r",
                  "    pm.response.to.have.status(200);\r",
                  "});\r",
                  "\r",
                  "let res = pm.response.json();\r",
                  "pm.environment.set(\"itemId\", res.data.itemId);"
                ],
                "type": "text/javascript",
                "packages": {},
                "requests": {}
              }
            },
            {
              "listen": "prerequest",
              "script": {
                "exec": [
                  ""
                ],
                "type": "text/javascript",
                "packages": {},
                "requests": {}
              }
            }
          ],
          "request": {
            "auth": {
              "type": "bearer",
              "bearer": [
                {
                  "key": "token",
                  "value": "eyJhbGciOiJIUzI1NiJ9.eyJzdWIiOiJ0aHJlZXN3b3Jkc3R5bGVAZ21haWwuY29tIFNIT1BQRVIiLCJleHAiOjE3NzU4MzQyNDQsImlhdCI6MTc3NTc5ODI0NH0.aTHeyGY3QY_qF8UqVTcxAu_m6gwQq47ylvTnQW2ch78",
                  "type": "string"
                }
              ]
            },
            "method": "PUT",
            "header": [],
            "body": {
              "mode": "raw",
              "raw": "{\r\n  \"productId\": 57,\r\n  \"quantity\": 3\r\n}",
              "options": {
                "raw": {
                  "language": "json"
                }
              }
            },
            "url": {
              "raw": "{{base_url}}/shoppers/{{shopperId}}/carts/{{itemId}}",
              "host": [
                "{{base_url}}"
              ],
              "path": [
                "shoppers",
                "{{shopperId}}",
                "carts",
                "{{itemId}}"
              ]
            }
          },
          "response": []
        },
        {
          "name": "New Request",
          "request": {
            "auth": {
              "type": "bearer",
              "bearer": [
                {
                  "key": "token",
                  "value": "eyJhbGciOiJIUzI1NiJ9.eyJzdWIiOiJ0aHJlZXN3b3Jkc3R5bGVAZ21haWwuY29tIFNIT1BQRVIiLCJleHAiOjE3NzU4MzQyNDQsImlhdCI6MTc3NTc5ODI0NH0.aTHeyGY3QY_qF8UqVTcxAu_m6gwQq47ylvTnQW2ch78",
                  "type": "string"
                }
              ]
            },
            "method": "DELETE",
            "header": [],
            "url": {
              "raw": "{{base_url}}/shoppers/{{shopperId}}/carts/{{productId}}",
              "host": [
                "{{base_url}}"
              ],
              "path": [
                "shoppers",
                "{{shopperId}}",
                "carts",
                "{{productId}}"
              ]
            }
          },
          "response": []
        }
      ]
    },
    {
      "name": "Shopper Order",
      "item": [
        {
          "name": "Order History",
          "request": {
            "auth": {
              "type": "bearer",
              "bearer": [
                {
                  "key": "token",
                  "value": "eyJhbGciOiJIUzI1NiJ9.eyJzdWIiOiJ0aHJlZXN3b3Jkc3R5bGVAZ21haWwuY29tIFNIT1BQRVIiLCJleHAiOjE3NzU4MzQyNDQsImlhdCI6MTc3NTc5ODI0NH0.aTHeyGY3QY_qF8UqVTcxAu_m6gwQq47ylvTnQW2ch78",
                  "type": "string"
                }
              ]
            },
            "method": "GET",
            "header": [],
            "url": {
              "raw": "{{base_url}}/shoppers/{{shopperId}}/orders",
              "host": [
                "{{base_url}}"
              ],
              "path": [
                "shoppers",
                "{{shopperId}}",
                "orders"
              ]
            }
          },
          "response": []
        },
        {
          "name": "Place Order from Cart",
          "event": [
            {
              "listen": "test",
              "script": {
                "exec": [
                  "pm.test(\"Status code is 201\", function () {\r",
                  "    pm.response.to.have.status(201);\r",
                  "});\r",
                  "\r",
                  "let res = pm.response.json();\r",
                  "pm.environment.set(\"orderId\" , res.data.orderId);\r",
                  ""
                ],
                "type": "text/javascript",
                "packages": {},
                "requests": {}
              }
            },
            {
              "listen": "prerequest",
              "script": {
                "exec": [],
                "type": "text/javascript"
              }
            }
          ],
          "request": {
            "auth": {
              "type": "bearer",
              "bearer": [
                {
                  "key": "token",
                  "value": "eyJhbGciOiJIUzI1NiJ9.eyJzdWIiOiJ0aHJlZXN3b3Jkc3R5bGVAZ21haWwuY29tIFNIT1BQRVIiLCJleHAiOjE3NzU4MzQyNDQsImlhdCI6MTc3NTc5ODI0NH0.aTHeyGY3QY_qF8UqVTcxAu_m6gwQq47ylvTnQW2ch78",
                  "type": "string"
                }
              ]
            },
            "method": "POST",
            "header": [],
            "body": {
              "mode": "raw",
              "raw": "{\r\n  \"address\": {\r\n    \"addressId\": {{addressId}},\r\n    \"buildingInfo\": \"string\",\r\n    \"city\": \"string\",\r\n    \"country\": \"string\",\r\n    \"landmark\": \"string\",\r\n    \"name\": \"string\",\r\n    \"phone\": \"string\",\r\n    \"pincode\": \"string\",\r\n    \"state\": \"string\",\r\n    \"streetInfo\": \"string\",\r\n    \"type\": \"string\"\r\n  },\r\n  \"paymentMode\": \"COD\"\r\n}",
              "options": {
                "raw": {
                  "language": "json"
                }
              }
            },
            "url": {
              "raw": "{{base_url}}/shoppers/{{shopperId}}/orders",
              "host": [
                "{{base_url}}"
              ],
              "path": [
                "shoppers",
                "{{shopperId}}",
                "orders"
              ]
            }
          },
          "response": []
        },
        {
          "name": "Update Order Status",
          "event": [
            {
              "listen": "test",
              "script": {
                "exec": [
                  "pm.test(\"Status code is 200\", function () {\r",
                  "    pm.response.to.have.status(200);\r",
                  "});\r",
                  "let res  = pm.response.json();\r",
                  "pm.environment.set(\"orderStatus\" , res.data.orderStatus);"
                ],
                "type": "text/javascript",
                "packages": {},
                "requests": {}
              }
            },
            {
              "listen": "prerequest",
              "script": {
                "exec": [],
                "type": "text/javascript"
              }
            }
          ],
          "request": {
            "auth": {
              "type": "bearer",
              "bearer": [
                {
                  "key": "token",
                  "value": "eyJhbGciOiJIUzI1NiJ9.eyJzdWIiOiJ0aHJlZXN3b3Jkc3R5bGVAZ21haWwuY29tIFNIT1BQRVIiLCJleHAiOjE3NzU4MzQyNDQsImlhdCI6MTc3NTc5ODI0NH0.aTHeyGY3QY_qF8UqVTcxAu_m6gwQq47ylvTnQW2ch78",
                  "type": "string"
                }
              ]
            },
            "method": "PATCH",
            "header": [],
            "url": {
              "raw": "{{base_url}}/shoppers/{{shopperId}}/orders/{{orderId}}?status=DELIVERED",
              "host": [
                "{{base_url}}"
              ],
              "path": [
                "shoppers",
                "{{shopperId}}",
                "orders",
                "{{orderId}}"
              ],
              "query": [
                {
                  "key": "status",
                  "value": "DELIVERED"
                }
              ]
            }
          },
          "response": []
        },
        {
          "name": "Generate Invoice Copy",
          "request": {
            "auth": {
              "type": "bearer",
              "bearer": [
                {
                  "key": "token",
                  "value": "eyJhbGciOiJIUzI1NiJ9.eyJzdWIiOiJ0aHJlZXN3b3Jkc3R5bGVAZ21haWwuY29tIFNIT1BQRVIiLCJleHAiOjE3NzU4MzQyNDQsImlhdCI6MTc3NTc5ODI0NH0.aTHeyGY3QY_qF8UqVTcxAu_m6gwQq47ylvTnQW2ch78",
                  "type": "string"
                }
              ]
            },
            "method": "GET",
            "header": [],
            "url": {
              "raw": "{{base_url}}/shoppers/{{shopperId}}/orders/{{orderId}}/invoice",
              "host": [
                "{{base_url}}"
              ],
              "path": [
                "shoppers",
                "{{shopperId}}",
                "orders",
                "{{orderId}}",
                "invoice"
              ]
            }
          },
          "response": []
        }
      ]
    },
    {
      "name": "Shopper Product Review",
      "item": [
        {
          "name": "Add a review",
          "event": [
            {
              "listen": "test",
              "script": {
                "exec": [
                  "pm.test(\"Status code is 200\", function () {\r",
                  "    pm.response.to.have.status(200);\r",
                  "});\r",
                  "\r",
                  "let res = pm.response.json();\r",
                  "pm.environment.set(\"reviewId\" , res.data.reviewId);"
                ],
                "type": "text/javascript",
                "packages": {},
                "requests": {}
              }
            },
            {
              "listen": "prerequest",
              "script": {
                "exec": [],
                "type": "text/javascript"
              }
            }
          ],
          "request": {
            "auth": {
              "type": "bearer",
              "bearer": [
                {
                  "key": "token",
                  "value": "{{jwtToken}}",
                  "type": "string"
                }
              ]
            },
            "method": "POST",
            "header": [],
            "body": {
              "mode": "raw",
              "raw": "{\r\n  \"dateTime\": \"2026-04-10T06:48:19.869Z\",\r\n  \"description\": \"string\",\r\n  \"heading\": \"string\",\r\n  \"rating\": 5,\r\n  \"shopperId\": {{shopperId}},\r\n  \"shopperName\": \"string\"\r\n}",
              "options": {
                "raw": {
                  "language": "json"
                }
              }
            },
            "url": {
              "raw": "{{base_url}}/reviews?productId={{productId}}",
              "host": [
                "{{base_url}}"
              ],
              "path": [
                "reviews"
              ],
              "query": [
                {
                  "key": "productId",
                  "value": "{{productId}}"
                }
              ]
            }
          },
          "response": []
        },
        {
          "name": "Get all Reviews",
          "request": {
            "method": "GET",
            "header": [],
            "url": {
              "raw": "{{base_url}}/reviews/{{productId}}",
              "host": [
                "{{base_url}}"
              ],
              "path": [
                "reviews",
                "{{productId}}"
              ]
            }
          },
          "response": []
        },
        {
          "name": "New Request",
          "event": [
            {
              "listen": "test",
              "script": {
                "exec": [
                  "pm.test(\"Status code is 200\", function () {\r",
                  "    pm.response.to.have.status(200);\r",
                  "});\r",
                  "\r",
                  "let res = pm.response.json();\r",
                  "pm.environment.set(\"reviewId\" , res.data.reviewId);"
                ],
                "type": "text/javascript",
                "packages": {},
                "requests": {}
              }
            },
            {
              "listen": "prerequest",
              "script": {
                "exec": [],
                "type": "text/javascript"
              }
            }
          ],
          "request": {
            "auth": {
              "type": "bearer",
              "bearer": [
                {
                  "key": "token",
                  "value": "{{jwtToken}}",
                  "type": "string"
                }
              ]
            },
            "method": "PUT",
            "header": [],
            "body": {
              "mode": "raw",
              "raw": "{\r\n  \"dateTime\": \"2026-04-10T06:45:47.964Z\",\r\n  \"description\": \"string\",\r\n  \"heading\": \"string\",\r\n  \"rating\": 4,\r\n  \"shopperId\": {{shopperId}},\r\n  \"shopperName\": \"string\"\r\n}",
              "options": {
                "raw": {
                  "language": "json"
                }
              }
            },
            "url": {
              "raw": "{{base_url}}/reviews/{{reviewId}}?productId={{productId}}",
              "host": [
                "{{base_url}}"
              ],
              "path": [
                "reviews",
                "{{reviewId}}"
              ],
              "query": [
                {
                  "key": "productId",
                  "value": "{{productId}}"
                }
              ]
            }
          },
          "response": []
        },
        {
          "name": "Delete Review",
          "request": {
            "method": "DELETE",
            "header": [],
            "url": {
              "raw": "{{base_url}}/reviews/{{reviewId}}?productId={{productId}}",
              "host": [
                "{{base_url}}"
              ],
              "path": [
                "reviews",
                "{{reviewId}}"
              ],
              "query": [
                {
                  "key": "productId",
                  "value": "{{productId}}"
                }
              ]
            }
          },
          "response": []
        }
      ]
    }
  ]
}